pvss/__init__.py
pvss/asn1.py
pvss/cli.py
pvss/groups.py
pvss/pvss.py
pvss/qr.py
pvss/ristretto_255.py
pvss/zq.py
pvss-0.2.0.dist-info/entry_points.txt
pvss-0.2.0.dist-info/WHEEL
pvss-0.2.0.dist-info/METADATA
pvss-0.2.0.dist-info/RECORD
