Metadata-Version: 2.1
Name: pvss
Version: 0.2.0
Summary: Public Verifiable Secret Splitting in Python
Home-page: https://github.com/joernheissler/pvss
License: MIT
Keywords: pvss,secret sharing,secret splitting,shamir,zero knowledge,ristretto25519
Author: Jörn Heissler
Author-email: nosuchaddress@joern.heissler.de
Requires-Python: >=3.7,<4.0
Classifier: License :: OSI Approved :: MIT License
Classifier: Programming Language :: Python :: 3
Classifier: Programming Language :: Python :: 3.7
Classifier: Programming Language :: Python :: 3.8
Classifier: Topic :: Scientific/Engineering :: Mathematics
Classifier: Topic :: Security :: Cryptography
Classifier: Topic :: Software Development :: Libraries :: Python Modules
Provides-Extra: docs
Requires-Dist: asn1crypto (>=1.3.0,<2.0.0)
Requires-Dist: click (>=7.0,<8.0)
Requires-Dist: lazy (>=1.4,<2.0)
Requires-Dist: sphinx (>=2.4,<3.0); extra == "docs"
Requires-Dist: sphinx-rtd-theme (>=0.4,<0.5); extra == "docs"
Project-URL: Repository, https://github.com/joernheissler/pvss
